nonebot_plugin_daily_bing/__init__.py
nonebot_plugin_daily_bing/config.py
nonebot_plugin_daily_bing/css/dark.css
nonebot_plugin_daily_bing/css/light.css
nonebot_plugin_daily_bing/infopuuzzle.py
nonebot_plugin_daily_bing/py.typed
nonebot_plugin_daily_bing/utils.py
nonebot_plugin_daily_bing-1.0.1.dist-info/WHEEL
nonebot_plugin_daily_bing-1.0.1.dist-info/METADATA
nonebot_plugin_daily_bing-1.0.1.dist-info/RECORD
