Metadata-Version: 2.4
Name: nonebot-plugin-daily-bing
Version: 1.0.1
Summary: NoneBot 每日必应壁纸
Author: lyqgzbl
Author-email: lyqgzbl <122811297+lyqgzbl@users.noreply.github.com>
License-Expression: MIT
Requires-Dist: aiofiles>=24.1.0
Requires-Dist: httpx>=0.28.0,<1.0.0
Requires-Dist: nonebot2>=2.2.1,<3.0.0
Requires-Dist: nonebot-plugin-argot>=0.2.2
Requires-Dist: nonebot-plugin-alconna>=0.57.1,<1.0.0
Requires-Dist: nonebot-plugin-localstore>=0.7.4,<1.0.0
Requires-Dist: nonebot-plugin-htmlrender>=0.5.0,<1.0.0
Requires-Dist: nonebot-plugin-apscheduler>=0.5.0,<1.0.0
Requires-Python: >=3.10, <4.0
Project-URL: documentation, https://github.com/lyqgzbl/nonebot-plugin-daily-bing#readme
Project-URL: homepage, https://github.com/lyqgzbl/nonebot-plugin-daily-bing
Project-URL: repository, https://github.com/lyqgzbl/nonebot-plugin-daily-bing
